{
  "annotations": {
    "list": [
      {
        "builtIn": 1,
        "datasource": {
          "type": "grafana",
          "uid": "-- Grafana --"
        },
        "enable": true,
        "hide": true,
        "iconColor": "rgba(0, 211, 255, 1)",
        "name": "Annotations & Alerts",
        "type": "dashboard"
      }
    ]
  },
  "editable": true,
  "fiscalYearStartMonth": 0,
  "graphTooltip": 0,
  "id": 249,
  "links": [],
  "panels": [
    {
      "datasource": {
        "type": "prometheus",
        "uid": "prometheus"
      },
      "fieldConfig": {
        "defaults": {
          "color": {
            "mode": "palette-classic"
          },
          "custom": {
            "axisBorderShow": false,
            "axisCenteredZero": false,
            "axisColorMode": "text",
            "axisLabel": "",
            "axisPlacement": "auto",
            "barAlignment": 0,
            "barWidthFactor": 0.6,
            "drawStyle": "line",
            "fillOpacity": 13,
            "gradientMode": "none",
            "hideFrom": {
              "legend": false,
              "tooltip": false,
              "viz": false
            },
            "insertNulls": false,
            "lineInterpolation": "linear",
            "lineWidth": 1,
            "pointSize": 5,
            "scaleDistribution": {
              "type": "linear"
            },
            "showPoints": "auto",
            "showValues": false,
            "spanNulls": false,
            "stacking": {
              "group": "A",
              "mode": "none"
            },
            "thresholdsStyle": {
              "mode": "off"
            }
          },
          "mappings": [],
          "thresholds": {
            "mode": "absolute",
            "steps": [
              {
                "color": "green",
                "value": 0
              },
              {
                "color": "red",
                "value": 80
              }
            ]
          },
          "unit": "bytes"
        },
        "overrides": [
          {
            "matcher": {
              "id": "byName",
              "options": "Memory Usage"
            },
            "properties": [
              {
                "id": "custom.lineWidth",
                "value": 2
              },
              {
                "id": "custom.fillOpacity",
                "value": 20
              },
              {
                "id": "custom.gradientMode",
                "value": "opacity"
              },
              {
                "id": "color",
                "value": {
                  "fixedColor": "dark-orange",
                  "mode": "fixed"
                }
              }
            ]
          }
        ]
      },
      "gridPos": {
        "h": 9,
        "w": 12,
        "x": 0,
        "y": 0
      },
      "id": 2,
      "options": {
        "legend": {
          "calcs": [],
          "displayMode": "table",
          "placement": "bottom",
          "showLegend": true
        },
        "tooltip": {
          "hideZeros": false,
          "mode": "single",
          "sort": "none"
        }
      },
      "pluginVersion": "12.3.0",
      "targets": [
        {
          "datasource": {
            "type": "prometheus",
            "uid": "c55566e7-988b-4865-a422-3a012b3317d4"
          },
          "editorMode": "code",
          "expr": "sum(container_memory_usage_bytes{namespace=\"$namespace\", pod=~\"$daemonset-.*\", container!=\"POD\"})",
          "instant": false,
          "legendFormat": "Memory Usage",
          "range": true,
          "refId": "A"
        }
      ],
      "title": "Memory usage",
      "type": "timeseries"
    },
    {
      "datasource": {
        "type": "prometheus",
        "uid": "prometheus"
      },
      "fieldConfig": {
        "defaults": {
          "color": {
            "mode": "palette-classic"
          },
          "custom": {
            "axisBorderShow": false,
            "axisCenteredZero": false,
            "axisColorMode": "text",
            "axisLabel": "",
            "axisPlacement": "auto",
            "barAlignment": 0,
            "barWidthFactor": 0.6,
            "drawStyle": "line",
            "fillOpacity": 13,
            "gradientMode": "none",
            "hideFrom": {
              "legend": false,
              "tooltip": false,
              "viz": false
            },
            "insertNulls": false,
            "lineInterpolation": "linear",
            "lineWidth": 1,
            "pointSize": 5,
            "scaleDistribution": {
              "type": "linear"
            },
            "showPoints": "auto",
            "showValues": false,
            "spanNulls": false,
            "stacking": {
              "group": "A",
              "mode": "none"
            },
            "thresholdsStyle": {
              "mode": "off"
            }
          },
          "mappings": [],
          "thresholds": {
            "mode": "absolute",
            "steps": [
              {
                "color": "green",
                "value": 0
              },
              {
                "color": "red",
                "value": 80
              }
            ]
          },
          "unit": "cores"
        },
        "overrides": [
          {
            "matcher": {
              "id": "byName",
              "options": "CPU Usage (cores)"
            },
            "properties": [
              {
                "id": "custom.lineWidth",
                "value": 2
              },
              {
                "id": "custom.fillOpacity",
                "value": 20
              },
              {
                "id": "custom.gradientMode",
                "value": "opacity"
              },
              {
                "id": "color",
                "value": {
                  "fixedColor": "semi-dark-blue",
                  "mode": "fixed"
                }
              }
            ]
          }
        ]
      },
      "gridPos": {
        "h": 9,
        "w": 12,
        "x": 12,
        "y": 0
      },
      "id": 1,
      "options": {
        "legend": {
          "calcs": [],
          "displayMode": "table",
          "placement": "bottom",
          "showLegend": true
        },
        "tooltip": {
          "hideZeros": false,
          "mode": "single",
          "sort": "none"
        }
      },
      "pluginVersion": "12.3.0",
      "targets": [
        {
          "datasource": {
            "type": "prometheus",
            "uid": "c55566e7-988b-4865-a422-3a012b3317d4"
          },
          "editorMode": "code",
          "expr": "sum(rate(container_cpu_usage_seconds_total{namespace=\"$namespace\", pod=~\"$daemonset-.*\", container!=\"POD\"}[5m]))",
          "instant": false,
          "legendFormat": "CPU Usage (cores)",
          "range": true,
          "refId": "A"
        }
      ],
      "title": "CPU Usage (cores)",
      "type": "timeseries"
    },
    {
      "datasource": {
        "type": "prometheus",
        "uid": "prometheus"
      },
      "fieldConfig": {
        "defaults": {
          "color": {
            "mode": "palette-classic"
          },
          "custom": {
            "axisBorderShow": false,
            "axisCenteredZero": false,
            "axisColorMode": "text",
            "axisLabel": "",
            "axisPlacement": "auto",
            "barAlignment": 0,
            "barWidthFactor": 0.6,
            "drawStyle": "line",
            "fillOpacity": 13,
            "gradientMode": "none",
            "hideFrom": {
              "legend": false,
              "tooltip": false,
              "viz": false
            },
            "insertNulls": false,
            "lineInterpolation": "linear",
            "lineWidth": 1,
            "pointSize": 5,
            "scaleDistribution": {
              "type": "linear"
            },
            "showPoints": "auto",
            "showValues": false,
            "spanNulls": false,
            "stacking": {
              "group": "A",
              "mode": "none"
            },
            "thresholdsStyle": {
              "mode": "off"
            }
          },
          "mappings": [],
          "thresholds": {
            "mode": "absolute",
            "steps": [
              {
                "color": "green",
                "value": 0
              },
              {
                "color": "red",
                "value": 80
              }
            ]
          },
          "unit": "bytes"
        },
        "overrides": [
          {
            "matcher": {
              "id": "byName",
              "options": "Network I/O"
            },
            "properties": [
              {
                "id": "custom.lineWidth",
                "value": 2
              },
              {
                "id": "custom.fillOpacity",
                "value": 20
              },
              {
                "id": "custom.gradientMode",
                "value": "opacity"
              },
              {
                "id": "color",
                "value": {
                  "fixedColor": "semi-dark-orange",
                  "mode": "fixed"
                }
              },
              {
                "id": "custom.pointSize",
                "value": 0
              }
            ]
          }
        ]
      },
      "gridPos": {
        "h": 10,
        "w": 12,
        "x": 0,
        "y": 9
      },
      "id": 3,
      "options": {
        "legend": {
          "calcs": [],
          "displayMode": "table",
          "placement": "bottom",
          "showLegend": true
        },
        "tooltip": {
          "hideZeros": false,
          "mode": "single",
          "sort": "none"
        }
      },
      "pluginVersion": "12.3.0",
      "targets": [
        {
          "datasource": {
            "type": "prometheus",
            "uid": "c55566e7-988b-4865-a422-3a012b3317d4"
          },
          "editorMode": "code",
          "expr": "sum(rate(container_network_receive_bytes_total{namespace=\"$namespace\", pod=~\"$daemonset-.*\"}[5m]) + rate(container_network_transmit_bytes_total{namespace=\"$namespace\", pod=~\"$daemonset-.*\"}[5m]))",
          "instant": false,
          "legendFormat": "Network I/O",
          "range": true,
          "refId": "A"
        }
      ],
      "title": "Network I/O",
      "type": "timeseries"
    },
    {
      "datasource": {
        "type": "prometheus",
        "uid": "prometheus"
      },
      "fieldConfig": {
        "defaults": {
          "color": {
            "fixedColor": "blue",
            "mode": "fixed"
          },
          "mappings": [],
          "thresholds": {
            "mode": "absolute",
            "steps": [
              {
                "color": "green",
                "value": 0
              },
              {
                "color": "red",
                "value": 80
              }
            ]
          },
          "unit": "short"
        },
        "overrides": []
      },
      "gridPos": {
        "h": 5,
        "w": 6,
        "x": 12,
        "y": 9
      },
      "id": 4,
      "options": {
        "colorMode": "value",
        "graphMode": "area",
        "justifyMode": "auto",
        "orientation": "auto",
        "percentChangeColorMode": "standard",
        "reduceOptions": {
          "calcs": [
            "lastNotNull"
          ],
          "fields": "",
          "values": false
        },
        "showPercentChange": false,
        "textMode": "auto",
        "wideLayout": true
      },
      "pluginVersion": "12.3.0",
      "targets": [
        {
          "datasource": {
            "type": "prometheus",
            "uid": "c55566e7-988b-4865-a422-3a012b3317d4"
          },
          "editorMode": "code",
          "expr": "kube_daemonset_status_desired_number_scheduled{namespace=\"$namespace\", daemonset=\"$daemonset\"}",
          "instant": false,
          "legendFormat": "Desired Replicas",
          "range": true,
          "refId": "A"
        }
      ],
      "title": "Desired Replicas",
      "type": "stat"
    },
    {
      "datasource": {
        "type": "prometheus",
        "uid": "prometheus"
      },
      "fieldConfig": {
        "defaults": {
          "color": {
            "fixedColor": "blue",
            "mode": "fixed"
          },
          "mappings": [],
          "thresholds": {
            "mode": "absolute",
            "steps": [
              {
                "color": "green",
                "value": 0
              },
              {
                "color": "red",
                "value": 80
              }
            ]
          },
          "unit": "short"
        },
        "overrides": []
      },
      "gridPos": {
        "h": 5,
        "w": 6,
        "x": 18,
        "y": 9
      },
      "id": 5,
      "options": {
        "colorMode": "value",
        "graphMode": "area",
        "justifyMode": "auto",
        "orientation": "auto",
        "percentChangeColorMode": "standard",
        "reduceOptions": {
          "calcs": [
            "lastNotNull"
          ],
          "fields": "",
          "values": false
        },
        "showPercentChange": false,
        "textMode": "auto",
        "wideLayout": true
      },
      "pluginVersion": "12.3.0",
      "targets": [
        {
          "datasource": {
            "type": "prometheus",
            "uid": "c55566e7-988b-4865-a422-3a012b3317d4"
          },
          "editorMode": "code",
          "expr": "kube_daemonset_status_number_available{namespace=\"$namespace\", daemonset=\"$daemonset\"}",
          "instant": false,
          "legendFormat": "Available Replicas",
          "range": true,
          "refId": "A"
        }
      ],
      "title": "Available Replicas",
      "type": "stat"
    },
    {
      "datasource": {
        "type": "prometheus",
        "uid": "prometheus"
      },
      "fieldConfig": {
        "defaults": {
          "color": {
            "fixedColor": "blue",
            "mode": "fixed"
          },
          "mappings": [],
          "thresholds": {
            "mode": "absolute",
            "steps": [
              {
                "color": "green",
                "value": 0
              },
              {
                "color": "red",
                "value": 80
              }
            ]
          },
          "unit": "short"
        },
        "overrides": []
      },
      "gridPos": {
        "h": 5,
        "w": 6,
        "x": 12,
        "y": 14
      },
      "id": 6,
      "options": {
        "colorMode": "value",
        "graphMode": "area",
        "justifyMode": "auto",
        "orientation": "auto",
        "percentChangeColorMode": "standard",
        "reduceOptions": {
          "calcs": [
            "lastNotNull"
          ],
          "fields": "",
          "values": false
        },
        "showPercentChange": false,
        "textMode": "auto",
        "wideLayout": true
      },
      "pluginVersion": "12.3.0",
      "targets": [
        {
          "datasource": {
            "type": "prometheus",
            "uid": "c55566e7-988b-4865-a422-3a012b3317d4"
          },
          "editorMode": "code",
          "expr": "kube_daemonset_status_observed_generation{namespace=\"$namespace\", daemonset=\"$daemonset\"}",
          "instant": false,
          "legendFormat": "Observed Generation",
          "range": true,
          "refId": "A"
        }
      ],
      "title": "Observed Generation",
      "type": "stat"
    },
    {
      "datasource": {
        "type": "prometheus",
        "uid": "prometheus"
      },
      "fieldConfig": {
        "defaults": {
          "color": {
            "fixedColor": "blue",
            "mode": "fixed"
          },
          "mappings": [],
          "thresholds": {
            "mode": "absolute",
            "steps": [
              {
                "color": "green",
                "value": 0
              },
              {
                "color": "red",
                "value": 80
              }
            ]
          },
          "unit": "short"
        },
        "overrides": []
      },
      "gridPos": {
        "h": 5,
        "w": 6,
        "x": 18,
        "y": 14
      },
      "id": 7,
      "options": {
        "colorMode": "value",
        "graphMode": "area",
        "justifyMode": "auto",
        "orientation": "auto",
        "percentChangeColorMode": "standard",
        "reduceOptions": {
          "calcs": [
            "lastNotNull"
          ],
          "fields": "",
          "values": false
        },
        "showPercentChange": false,
        "textMode": "auto",
        "wideLayout": true
      },
      "pluginVersion": "12.3.0",
      "targets": [
        {
          "datasource": {
            "type": "prometheus",
            "uid": "c55566e7-988b-4865-a422-3a012b3317d4"
          },
          "editorMode": "code",
          "expr": "kube_daemonset_metadata_generation{namespace=\"$namespace\", daemonset=\"$daemonset\"}",
          "instant": false,
          "legendFormat": "__auto",
          "range": true,
          "refId": "A"
        }
      ],
      "title": "Metadata Generation",
      "type": "stat"
    },
    {
      "datasource": {
        "type": "prometheus",
        "uid": "prometheus"
      },
      "fieldConfig": {
        "defaults": {
          "color": {
            "mode": "palette-classic"
          },
          "custom": {
            "axisBorderShow": false,
            "axisCenteredZero": false,
            "axisColorMode": "text",
            "axisLabel": "",
            "axisPlacement": "auto",
            "barAlignment": 0,
            "drawStyle": "line",
            "fillOpacity": 13,
            "gradientMode": "none",
            "hideFrom": {
              "legend": false,
              "tooltip": false,
              "viz": false
            },
            "insertNulls": false,
            "lineInterpolation": "linear",
            "lineWidth": 1,
            "pointSize": 5,
            "scaleDistribution": {
              "type": "linear"
            },
            "showPoints": "auto",
            "spanNulls": false,
            "stacking": {
              "group": "A",
              "mode": "none"
            },
            "thresholdsStyle": {
              "mode": "off"
            }
          },
          "mappings": [],
          "thresholds": {
            "mode": "absolute",
            "steps": [
              {
                "color": "green"
              },
              {
                "color": "red",
                "value": 80
              }
            ]
          },
          "unit": "bytes"
        },
        "overrides": [
          {
            "matcher": {
              "id": "byName",
              "options": "Desired"
            },
            "properties": [
              {
                "id": "custom.axisPlacement",
                "value": "right"
              },
              {
                "id": "custom.lineWidth",
                "value": 2
              },
              {
                "id": "custom.fillOpacity",
                "value": 20
              },
              {
                "id": "custom.gradientMode",
                "value": "opacity"
              },
              {
                "id": "custom.showPoints",
                "value": "never"
              },
              {
                "id": "color",
                "value": {
                  "fixedColor": "dark-orange",
                  "mode": "fixed"
                }
              }
            ]
          },
          {
            "matcher": {
              "id": "byName",
              "options": "Avaliable"
            },
            "properties": [
              {
                "id": "custom.drawStyle",
                "value": "line"
              },
              {
                "id": "custom.lineInterpolation",
                "value": "linear"
              },
              {
                "id": "custom.barAlignment",
                "value": 0
              },
              {
                "id": "custom.lineWidth",
                "value": 2
              },
              {
                "id": "custom.fillOpacity",
                "value": 20
              },
              {
                "id": "custom.gradientMode",
                "value": "opacity"
              },
              {
                "id": "custom.showPoints",
                "value": "never"
              },
              {
                "id": "color",
                "value": {
                  "fixedColor": "semi-dark-blue",
                  "mode": "fixed"
                }
              }
            ]
          }
        ]
      },
      "gridPos": {
        "h": 12,
        "w": 24,
        "x": 0,
        "y": 19
      },
      "id": 8,
      "options": {
        "legend": {
          "calcs": [],
          "displayMode": "table",
          "placement": "right",
          "showLegend": true,
          "sortBy": "Name",
          "sortDesc": true
        },
        "tooltip": {
          "mode": "single",
          "sort": "none"
        }
      },
      "targets": [
        {
          "datasource": {
            "type": "prometheus",
            "uid": "c55566e7-988b-4865-a422-3a012b3317d4"
          },
          "editorMode": "code",
          "expr": "kube_daemonset_status_desired_number_scheduled{namespace=\"$namespace\", daemonset=\"$daemonset\"}",
          "instant": false,
          "legendFormat": "Desired",
          "range": true,
          "refId": "A"
        },
        {
          "datasource": {
            "type": "prometheus",
            "uid": "c55566e7-988b-4865-a422-3a012b3317d4"
          },
          "editorMode": "code",
          "expr": "kube_daemonset_status_number_available{namespace=\"$namespace\", daemonset=\"$daemonset\"}",
          "hide": false,
          "instant": false,
          "legendFormat": "Avaliable",
          "range": true,
          "refId": "B"
        }
      ],
      "title": "Replicas Over Time",
      "type": "timeseries"
    }
  ],
  "preload": false,
  "refresh": "",
  "schemaVersion": 42,
  "tags": [],
  "templating": {
    "list": [
      {
        "current": {
          "text": "ops",
          "value": "ops"
        },
        "datasource": {
          "type": "prometheus",
          "uid": "prometheus"
        },
        "definition": "label_values(kube_daemonset_status_desired_number_scheduled{namespace=\"ops\"},namespace)",
        "includeAll": false,
        "label": "Namespace",
        "name": "namespace",
        "options": [],
        "query": {
          "qryType": 1,
          "query": "label_values(kube_daemonset_status_desired_number_scheduled{namespace=\"ops\"},namespace)",
          "refId": "PrometheusVariableQueryEditor-VariableQuery"
        },
        "refresh": 1,
        "regex": "",
        "type": "query"
      },
      {
        "current": {
          "text": "cadvisor",
          "value": "cadvisor"
        },
        "datasource": {
          "type": "prometheus",
          "uid": "prometheus"
        },
        "definition": "label_values(kube_daemonset_status_desired_number_scheduled{namespace=\"$namespace\"},daemonset)",
        "includeAll": false,
        "label": "DaemonSet",
        "name": "daemonset",
        "options": [],
        "query": {
          "qryType": 1,
          "query": "label_values(kube_daemonset_status_desired_number_scheduled{namespace=\"$namespace\"},daemonset)",
          "refId": "PrometheusVariableQueryEditor-VariableQuery"
        },
        "refresh": 1,
        "regex": "",
        "type": "query"
      }
    ]
  },
  "time": {
    "from": "now-6h",
    "to": "now"
  },
  "timepicker": {},
  "timezone": "",
  "title": "Daemonset-Dashbaord",
  "uid": "c0a13113-0b5a-42c2-8bc4-3f38c5e8947c",
  "version": 1
}